{"type": "Loop", "name": "Start", "children": [{"type": "Selection", "name": "Execuation", "children": [{"type": "Loop", "name": "CheckUser", "children": [{"type": "Condition", "name": "nobody", "children": []}]}, {"type": "Condition", "name": "initialization", "children": []}, {"type": "Loop", "name": "MainLoop", "children": [{"type": "Sequence", "name": "MainExecuation", "children": [{"type": "Condition", "name": "updateUser", "children": []}, {"type": "Condition", "name": "checkEnd", "children": []}, {"type": "Selection", "name": "Interaction", "children": [{"type": "Condition", "name": "checkFaceEmotion", "children": []}, {"type": "Condition", "name": "noInput", "children": []}, {"type": "Condition", "name": "checkName", "children": []}, {"type": "Condition", "name": "learnKnowledge", "children": []}, {"type": "Condition", "name": "checkNumPeople", "children": []}, {"type": "Condition", "name": "pardon", "children": []}, {"type": "Condition", "name": "shutUp", "children": []}, {"type": "Condition", "name": "repeat", "children": []}, {"type": "Sequence", "name": "checkMail", "children": [{"type": "Condition", "name": "askForMail", "children": []}, {"type": "Selection", "name": "ProcessEmail", "children": [{"type": "Selection", "name": "sendEmail", "children": [{"type": "Loop", "name": "Loop_11", "children": [{"type": "Selection", "name": "Select_11", "children": [{"type": "Condition", "name": "askWhom", "children": []}, {"type": "Condition", "name": "noConfirm", "children": []}]}]}, {"type": "Sequence", "name": "Seq_1", "children": [{"type": "Condition", "name": "known", "children": []}, {"type": "Condition", "name": "askEmail", "children": []}]}, {"type": "Loop", "name": "Loop_21", "children": [{"type": "Selection", "name": "Select_21", "children": [{"type": "Condition", "name": "askTitle", "children": []}, {"type": "Condition", "name": "noConfirm", "children": []}]}]}, {"type": "Loop", "name": "Loop_31", "children": [{"type": "Selection", "name": "Select_31", "children": [{"type": "Condition", "name": "askContent", "children": []}, {"type": "Condition", "name": "noConfirm", "children": []}]}]}, {"type": "Condition", "name": "send", "children": []}]}, {"type": "Condition", "name": "quitEmail", "children": []}]}]}, {"type": "Selection", "name": "response", "children": [{"type": "Condition", "name": "analyzeInput", "children": []}, {"type": "Condition", "name": "updateEmotion", "children": []}, {"type": "Sequence", "name": "reply", "children": [{"type": "Selection", "name": "Answer", "children": [{"type": "Condition", "name": "askMemory", "children": []}, {"type": "Condition", "name": "askChatbot", "children": []}]}, {"type": "Condition", "name": "addQuestion", "children": []}]}]}]}]}]}, {"type": "Condition", "name": "quit", "children": []}]}]}